site2markdown/__init__.py
site2markdown/filters.py
site2markdown/formatters.py
site2markdown/processor.py
site2markdown/readers.py
site2markdown/table_converter.py
site2markdown/urltomarkdown.py
site2markdown-1.0.2.dist-info/licenses/LICENSE
site2markdown-1.0.2.dist-info/METADATA
site2markdown-1.0.2.dist-info/WHEEL
site2markdown-1.0.2.dist-info/top_level.txt
site2markdown-1.0.2.dist-info/RECORD
