Metadata-Version: 2.4
Name: site2markdown
Version: 1.0.2
Summary: Convert URL content to markdown for better LLM context.
Author: Sumit Banik
Author-email: Sumit Banik <sumitbanik02@gmail.com>
Classifier: Programming Language :: Python :: 3
Classifier: License :: OSI Approved :: MIT License
Classifier: Operating System :: OS Independent
Requires-Python: >=3.7
License-File: LICENSE
Requires-Dist: requests>=2.31.0
Requires-Dist: beautifulsoup4>=4.12.0
Requires-Dist: lxml>=4.9.0
Requires-Dist: html2text>=2020.1.16
Requires-Dist: readability-lxml>=0.8.1
Dynamic: author
Dynamic: license-file
Dynamic: requires-python
